codeaira/__init__.py
codeaira/client.py
codeaira/config.py
codeaira/exceptions.py
codeaira/models.py
codeaira/utils.py
codeaira_python-0.5.0.dist-info/licenses/LICENSE
codeaira_python-0.5.0.dist-info/METADATA
codeaira_python-0.5.0.dist-info/WHEEL
codeaira_python-0.5.0.dist-info/top_level.txt
codeaira_python-0.5.0.dist-info/RECORD
