Metadata-Version: 2.4
Name: codeaira-python
Version: 0.5.0
Summary: A Python client library for the CodeAira API
Author-email: karthik <rskarthik96@gmail.com>
License: 
Classifier: License :: OSI Approved :: Apache Software License
Classifier: Programming Language :: Python :: 3.9
Requires-Python: >=3.9
License-File: LICENSE
Requires-Dist: pydantic>=2.11.7
Requires-Dist: pydantic-settings>=2.10.1
Requires-Dist: requests>=2.32.5
Dynamic: license-file
